SignExtender.v
module SignExtender(BusImm, Imm26, Ctrl); 
   output [63:0] BusImm; // 64 bit
   input [25:0] Imm26; // 26 bit
   // old Ctrl (without MOVZ): input [1:0] Ctrl; // 2 bit
   input [2:0] 	Ctrl; // three bits wide to include MOVZ instruction
   
  
   // temp TA told us to write the code without always block, as this method is much more straightforward. 
   assign BusImm =
		 (Ctrl == 3'b000) ? ({{38{Imm26[25]}}, Imm26[25:0]}):  // case B -> 26 + 38 = 64
                 (Ctrl == 3'b001) ? ({{45{Imm26[23]}}, Imm26[23:5]}):  // case CBZ -> 19 + 45 = 64
                 (Ctrl == 3'b010) ? ({{55{Imm26[20]}}, Imm26[20:12]}): // case D -> 9 + 55 = 64
                 (Ctrl == 3'b011) ? ({{52'b0}, Imm26[21:10]}):         // case I -> 12 + 52 = 64
	         (Ctrl == 3'b100) ? ({48'b0, Imm26[20:5]}):
		 (Ctrl == 3'b101) ? ({32'b0, Imm26[20:5], 16'b0}):
		 (Ctrl == 3'b110) ? ({16'b0, Imm26[20:5], 32'b0}):
		 (Ctrl == 3'b111) ? ({Imm26[20:5], 48'b0}): // case IM left shifted by x bits
                 0;
endmodule

DataMemory.v
`timescale 1ns / 1ps

`define SIZE 1024

module DataMemory(ReadData , Address , WriteData , MemoryRead , MemoryWrite , Clock);
   input [63:0]      WriteData;
   input [63:0]      Address;
   input             Clock, MemoryRead, MemoryWrite;
   output reg [63:0] ReadData;

   reg [7:0] 	     memBank [`SIZE-1:0];


   // This task is used to write arbitrary data to the Data Memory by
   // the intialization block.
   task initset;
      input [63:0] addr;
      input [63:0] data;
      begin
	 memBank[addr] =  data[63:56] ; // Big-endian for the win...
	 memBank[addr+1] =  data[55:48];
	 memBank[addr+2] =  data[47:40];
	 memBank[addr+3] =  data[39:32];
	 memBank[addr+4] =  data[31:24];
	 memBank[addr+5] =  data[23:16];
	 memBank[addr+6] =  data[15:8];
	 memBank[addr+7] =  data[7:0];
      end
   endtask


   initial
     begin
        // preseting some data in the data memory used by test #1

        // Address 0x0 gets 0x1
        initset( 64'h0,  64'h1);  //Counter variable
        initset( 64'h8,  64'ha);  //Part of mask
        initset( 64'h10, 64'h5);  //Other part of mask
        initset( 64'h18, 64'h0ffbea7deadbeeff); //big constant
        initset( 64'h20, 64'h0); //clearing space

        // Add any data you need for your tests here.

     end

   // This always block reads the data memory and places a double word
   // on the ReadData bus.
   always @(posedge Clock)
     begin
        if(MemoryRead)
          begin
             ReadData[63:56] <=  memBank[Address];
             ReadData[55:48] <=  memBank[Address+1];
             ReadData[47:40] <=  memBank[Address+2];
             ReadData[39:32] <=  memBank[Address+3];
             ReadData[31:24] <=  memBank[Address+4];
             ReadData[23:16] <=  memBank[Address+5];
             ReadData[15:8] <=  memBank[Address+6];
             ReadData[7:0] <=  memBank[Address+7];
          end
     end

   // This always block takes data from the WriteData bus and writes
   // it into the DataMemory.
   always @(posedge Clock)
     begin
        if(MemoryWrite)
          begin
             memBank[Address] <= #3 WriteData[63:56] ;
             memBank[Address+1] <= #3 WriteData[55:48];
             memBank[Address+2] <= #3 WriteData[47:40];
             memBank[Address+3] <= #3 WriteData[39:32];
             memBank[Address+4] <= #3 WriteData[31:24];
             memBank[Address+5] <= #3 WriteData[23:16];
             memBank[Address+6] <= #3 WriteData[15:8];
             memBank[Address+7] <= #3 WriteData[7:0];
             // Could be useful for debugging:
             // $display("Writing Address:%h Data:%h",Address, WriteData);
          end
     end
endmodule // THIS FILE IS COMPELTE

NextPClogic.v
module NextPClogic(NextPC, CurrentPC, SignExtImm64, Branch, ALUZero, Uncondbranch); 
   input [63:0] CurrentPC, SignExtImm64; 
   input	Branch, ALUZero, Uncondbranch; 
   output reg [63:0] NextPC; 

   /* write your code here */

   wire and1; // (Branch AND ZeroFlag) OR UncondBranch this is mux switch
   wire or1;
   assign and1 = Branch & ALUZero;
   assign or1 = and1 | Uncondbranch; // essentially (Branch & ALUZero) | (UncondBranch)
   
   always @(*) begin
      if (or1 == 1) // branch to specific line
	NextPC = CurrentPC + (SignExtImm64 << 2);  // word offset (lsl2bits) -> byte offset
      else // default case
	NextPC = CurrentPC + 4;
   end // always block


endmodule

ALU.v
`define AND   4'b0000
`define OR    4'b0001
`define ADD   4'b0010
`define SUB   4'b0110
`define PassB 4'b0111


module ALU(BusW, BusA, BusB, ALUCtrl, Zero);
    
    output  [63:0] BusW;
    input   [63:0] BusA, BusB;
    input   [3:0] ALUCtrl;
    output  Zero;
    
    reg     [63:0] BusW;
    
    always @(*) begin
        case(ALUCtrl)
            `AND: begin // h'0
                BusW = BusA & BusB; 
	     end
	    `OR: begin // h'1
	        BusW = BusA | BusB;
	     end
	    `ADD: begin // h'3
	        BusW = BusA + BusB;
	     end
	    `SUB: begin // h'6
	        BusW = BusA - BusB;
	     end
	    `PassB: begin //h'7
	        BusW = BusB;
            end
        endcase
    end // always @ (ALUCtrl or BusA or BusB)

   
   assign Zero = (BusW == 0);  //0 or 1; a statement: (BusW == 0)
   // if BusW == 0, Zero = 1
   // else if BusW != =, Zero = 0
   
 
endmodule // THIS FILE IS COMPLETE

RegisterFile.v
module RegisterFile(BusA, BusB, BusW, RW, RA, RB, RegWr, Clk);
    output [63:0] BusA; // 64 bits
    output [63:0] BusB;
    input [63:0] BusW;
    input [4:0] RW, RA, RB; // 5 bits
    input RegWr;
    input Clk;
    reg [63:0] registers [31:0]; // 32x64 register file
     
    assign #2 BusA = registers[RA]; // BusA gets the value of RA
    assign #2 BusB = registers[RB]; // BusB gets the value of RB

   initial
     registers[31] <= 0; // this is the Zero register, we don't want Reg[31] to equal anything but 0.

   
    always @ (negedge Clk) begin
        if(RegWr) // if RegWR == 1 (is high)
	  if (RW != 5'd31) // we want to update all registers EXCEPT the Zero Register
            registers[RW] <= #3 BusW;
       
    end
   
endmodule

SingleCycleControl.v
`define OPCODE_ANDREG 11'b?0001010???
`define OPCODE_ORRREG 11'b?0101010???
`define OPCODE_ADDREG 11'b?0?01011???
`define OPCODE_SUBREG 11'b?1?01011???

`define OPCODE_ADDIMM 11'b?0?10001???
`define OPCODE_SUBIMM 11'b?1?10001???

`define OPCODE_MOVZ   11'b110100101??

`define OPCODE_B      11'b?00101?????
`define OPCODE_CBZ    11'b?011010????

`define OPCODE_LDUR   11'b??111000010
`define OPCODE_STUR   11'b??111000000

module control(
	       output reg 	reg2loc,
	       output reg 	alusrc,
	       output reg 	mem2reg,
	       output reg 	regwrite,
	       output reg 	memread,
	       output reg 	memwrite,
	       output reg 	branch,
	       output reg 	uncond_branch,
	       output reg [3:0] aluop,
	       output reg [2:0] signop, // changed to be 3 bits for MOVZ
	       input [10:0] 	opcode
	       );

   always @(*)
     begin
	casez (opcode)

          /* Add cases here for each instruction your processor supports */
	 
	  `OPCODE_LDUR: // LDUR (D instruction)
	    begin
	       reg2loc       = 1'bx;
               uncond_branch = 1'b0;
               branch        = 1'b0;
               memread       = 1'b1;
               mem2reg       = 1'b1;
               memwrite      = 1'b0;
               alusrc        = 1'b1;
               regwrite      = 1'b1;
               aluop         = 4'b0010;
               signop        = 3'b010;
               $display("LDUR received");
	    end // case: `OPCODE_LDUR

	  `OPCODE_STUR: // STUR (D instruction)
	    begin
	       reg2loc       = 1'b1;
               uncond_branch = 1'b0;
               branch        = 1'b0;
               memread       = 1'b0;
               mem2reg       = 1'bx;
               memwrite      = 1'b1;
               alusrc        = 1'b1;
               regwrite      = 1'b0;
               aluop         = 4'b0010;
               signop        = 3'b010;
               $display("STUR received");
	    end // case: `OPCODE_STUR

	  `OPCODE_ADDREG: // ADDR (R instruction)
	    begin
	       reg2loc       = 1'b0;
               uncond_branch = 1'b0;
               branch        = 1'b0;
               memread       = 1'b0;
               mem2reg       = 1'b0;
               memwrite      = 1'b0;
               alusrc        = 1'b0;
               regwrite      = 1'b1;
               aluop         = 4'b0010;
               signop        = 3'bxxx;
               $display("ADDR received");
	    end // case: `OPCODE_ADDREG

	  `OPCODE_ADDIMM: // ADDI (I instruction)
	    begin
	       reg2loc       = 1'b0;
               uncond_branch = 1'b0;
               branch        = 1'b0;
               memread       = 1'b0;
               mem2reg       = 1'b0;
               memwrite      = 1'b0;
               alusrc        = 1'b0;
               regwrite      = 1'b1;
               aluop         = 4'b0010;
               signop        = 3'b011;
               $display("ADDI received");
	    end // case: `OPCODE_ADDIMM

	  `OPCODE_SUBREG: // SUBR (R instruction)
	    begin
	       reg2loc       = 1'b0;
               uncond_branch = 1'b0;
               branch        = 1'b0;
               memread       = 1'b0;
               mem2reg       = 1'b0;
               memwrite      = 1'b0;
               alusrc        = 1'b0;
               regwrite      = 1'b1;
               aluop         = 4'b0110;
               signop        = 3'bxxx;
               $display("SUBR received");
	    end // case: `OPCODE_SUBREG

	  `OPCODE_SUBIMM: // SUBI (I instruction)
	    begin
	       
	       reg2loc       = 1'b0;
               uncond_branch = 1'b0;
               branch        = 1'b0;
               memread       = 1'b0;
               mem2reg       = 1'b0;
               memwrite      = 1'b0;
               alusrc        = 1'b0;
               regwrite      = 1'b1;
               aluop         = 4'b0110;
               signop        = 3'b011;
               $display("SUBI received");
	    end // case: `OPCODE_SUBIMM

	  `OPCODE_ANDREG: // AND (R instruction)
	    begin
	       reg2loc       = 1'b0;
               uncond_branch = 1'b0;
               branch        = 1'b0;
               memread       = 1'b0;
               mem2reg       = 1'b0;
               memwrite      = 1'b0;
               alusrc        = 1'b0;
               regwrite      = 1'b1;
               aluop         = 4'b0000;
               signop        = 3'bxxx;
               $display("AND received");
	    end // case: `OPCODE_ANDREG

	  `OPCODE_ORRREG: // ORR (R instruction)
	    begin
	       reg2loc       = 1'b0;
               uncond_branch = 1'b0;
               branch        = 1'b0;
               memread       = 1'b0;
               mem2reg       = 1'b0;
               memwrite      = 1'b0;
               alusrc        = 1'b0;
               regwrite      = 1'b1;
               aluop         = 4'b0001;
               signop        = 3'bxxx;
               $display("ORR received");
	    end // case: `OPCODE_ORRREG

	  `OPCODE_CBZ: // CBZ (CBZ instruction)
	    begin
	       reg2loc       = 1'b1;
               uncond_branch = 1'b0;
               branch        = 1'b1;
               memread       = 1'b0;
               mem2reg       = 1'bx;
               memwrite      = 1'b0;
               alusrc        = 1'b0;
               regwrite      = 1'b0;
               aluop         = 4'b0111;
               signop        = 3'b001;
               $display("CBZ received");
	    end // case: `OPCODE_CBZ

	  `OPCODE_B: // B (B instruction)
	    begin
	       reg2loc       = 1'bx;
               uncond_branch = 1'b1;
               branch        = 1'bx;
               memread       = 1'b0;
               mem2reg       = 1'bx;
               memwrite      = 1'b0;
               alusrc        = 1'bx;
               regwrite      = 1'b0;
               aluop         = 4'bxxxx;
               signop        = 3'b000;
               $display("B received");
	    end // case: `OPCODE_B

	  `OPCODE_MOVZ: // MOVZ 1 (IM instruction)
	    begin
	       // IMPLEMENT:
	       reg2loc       = 1'bx;
               uncond_branch = 1'b0;
               branch        = 1'b0;
               memread       = 1'b0;
               mem2reg       = 1'b0;
               memwrite      = 1'b0;
               alusrc        = 1'b1;
               regwrite      = 1'b1;
               aluop         = 4'b0111;
               signop        = opcode[2:0]; //opcode[2:0]
               $display("MOVZ received");
	    end // case: `OPCODE_MOVZ
       
	endcase // casez (opcode)
	
     end // always @ (*)
endmodule

InstructionMemory.v
`timescale 1ns / 1ps
/*
 * Module: InstructionMemory
 *
 * Implements read-only instruction memory
 * 
 */
module InstructionMemory(Data, Address);
   parameter T_rd = 20;
   parameter MemSize = 40;
   
   output [31:0] Data;
   input [63:0]  Address;
   reg [31:0] 	 Data;
   
   /*
    * ECEN 350 Processor Test Functions
    * Texas A&M University
    */
   
   always @ (Address) begin

      case(Address)

	/* Test Program 1:
	 * Program loads constants from the data memory. Uses these constants to test
	 * the following instructions: LDUR, ORR, AND, CBZ, ADD, SUB, STUR and B.
	 * 
	 * Assembly code for test:
	 * 
	 * 0: LDUR X9, [XZR, 0x0]    //Load 1 into x9
	 * 4: LDUR X10, [XZR, 0x8]   //Load a into x10
	 * 8: LDUR X11, [XZR, 0x10]  //Load 5 into x11
	 * C: LDUR X12, [XZR, 0x18]  //Load big constant into x12
	 * 10: LDUR X13, [XZR, 0x20]  //load a 0 into X13
	 * 
	 * 14: ORR X10, X10, X11  //Create mask of 0xf
	 * 18: AND X12, X12, X10  //Mask off low order bits of big constant
	 * 
	 * loop:
	 * 1C: CBZ X12, end  //while X12 is not 0
	 * 20: ADD X13, X13, X9  //Increment counter in X13
	 * 24: SUB X12, X12, X9  //Decrement remainder of big constant in X12
	 * 28: B loop  //Repeat till X12 is 0
	 * 2C: STUR X13, [XZR, 0x20]  //store back the counter value into the memory location 0x20
	 */
	

	63'h000: Data = 32'hF84003E9; 
	63'h004: Data = 32'hF84083EA; 
	63'h008: Data = 32'hF84103EB; 
	63'h00c: Data = 32'hF84183EC; 
	63'h010: Data = 32'hF84203ED;
	63'h014: Data = 32'hAA0B014A;
	63'h018: Data = 32'h8A0A018C;
	63'h01c: Data = 32'hB400008C;
	63'h020: Data = 32'h8B0901AD;
	63'h024: Data = 32'hCB09018C;
	63'h028: Data = 32'h17FFFFFD;
	63'h02c: Data = 32'hF80203ED;
	63'h030: Data = 32'hF84203ED;  //One last load to place stored value on memdbus for test checking.
 
	/* Add code for your tests here */

	/* Test Program 2:
	 * Assembly code for test:
	 * 
	 * 0: LDUR X9, [XZR, 0x0]    // Load 0 into x9
	 * 4: MOVZ X10, #0xDEF0, lsl #0  // Register X10 is temp regA
	 * 8: ADD X9, X10, X9
	 * C: MOVZ X10, #0x9ABC, lsl #16
	 * 10: ADD X9, X10, X9
	 * 14: MOVZ X10, #0x5678, lsl #32
	 * 18: ADD X9, X10, X9
	 * 1C: MOVZ X10, #0x1234, lsl #48
	 * 20: ADD X9, X10, X9
	 * 24: STUR X9, [XZR, 0x28]
	 * 28: LDUR X10, [XZR, 0x28]
	 */
	
	63'h034: Data = 32'hCB090129;
	63'h038: Data = {11'b11010010100, 16'hDEF0, 5'd10};
	63'h03c: Data = 32'h8B090149;
	63'h040: Data = {11'b11010010101, 16'h9ABC, 5'd10};
	63'h044: Data = 32'h8B090149;
	63'h048: Data = {11'b11010010110, 16'h5678, 5'd10};
	63'h04c: Data = 32'h8B090149;
	63'h050: Data = {11'b11010010111, 16'h1234, 5'd10};
	63'h054: Data = 32'h8B090149;
	63'h058: Data = {11'b11111000000, 9'h28, 2'b00, 5'd31, 5'd9}; //{11'b, 9'h28, 2'b00, 5'd31, 5'd9}
	63'h05c: Data = {11'b11111000010, 9'h28, 2'b00, 5'd31, 5'd10};

	
	default: Data = 32'hXXXXXXXX;
      endcase
   end
endmodule

SingleCycleProc.v
// Implement timescale:
`timescale 1 ns / 1 ps

module singlecycle(
		   input 	     resetl,
		   input [63:0]      startpc,
		   output reg [63:0] currentpc,
		   output [63:0]     MemtoRegOut,  // this should be
						   // attached to the
						   // output of the
						   // MemtoReg Mux
		   input 	     CLK
		   );

   // Next PC connections
   wire [63:0] 			     nextpc;       // The next PC, to be updated on clock cycle

   // Instruction Memory connections
   wire [31:0] 			     instruction;  // The current instruction

   // Parts of instruction
   wire [4:0] 			     rd;            // The destination register
   wire [4:0] 			     rm;            // Operand 1
   wire [4:0] 			     rn;            // Operand 2
   wire [10:0] 			     opcode;

   // Control wires
   wire 			     reg2loc;
   wire 			     alusrc;
   wire 			     mem2reg;
   wire 			     regwrite;
   wire 			     memread;
   wire 			     memwrite;
   wire 			     branch;
   wire 			     uncond_branch;
   wire [3:0] 			     aluctrl;
   wire [2:0] 			     signop;

   // Register file connections
   wire [63:0] 			     regoutA;     // Output A
   wire [63:0] 			     regoutB;     // Output B

   // ALU connections
   wire [63:0] 			     aluout;
   wire 			     zero;

   // Sign Extender connections
   wire [63:0] 			     extimm;

   // Data Memory connections (IMPLEMENT):
   wire [63:0] 			     memoryout;
   wire [63:0] 			     aluMUXout;  

   // PC update logic
   always @(negedge CLK)
     begin
        if (resetl)
          currentpc <= #3 nextpc;
        else
          currentpc <= #3 startpc;
     end

   // Parts of instruction
   assign rd = instruction[4:0];
   assign rm = instruction[9:5];
   assign rn = reg2loc ? instruction[4:0] : instruction[20:16];
   assign opcode = instruction[31:21];

   // Complete remaining assigns (IMPLEMENT):
   assign aluMUXout = alusrc ? extimm : regoutB; // MUX 1
   assign MemtoRegOut = mem2reg ? memoryout : aluout; // MUX 2
   

   InstructionMemory imem( // InstructionMemory.v
			  .Data(instruction),
			  .Address(currentpc)
			  );

   control control( // SingleCycleControl.v
		   .reg2loc(reg2loc),
		   .alusrc(alusrc),
		   .mem2reg(mem2reg),
		   .regwrite(regwrite),
		   .memread(memread),
		   .memwrite(memwrite),
		   .branch(branch),
		   .uncond_branch(uncond_branch),
		   .aluop(aluctrl),
		   .signop(signop[2:0]),
		   .opcode(opcode)
		   );

     /*
    * Connect the remaining datapath elements below.
    * Do not forget any additional multiplexers that may be required.
    * (IMPLEMENT): 
    */

   RegisterFile regfile( // RegisterFile.v
			.BusA(regoutA),
			.BusB(regoutB),
			.BusW(MemtoRegOut),
			.RA(rm),
			.RB(rn),
			.RW(rd),
			.RegWr(regwrite),
			.Clk(CLK)
			);

    ALU alu( // ALU.v
            .BusW(aluout),
            .BusA(regoutA),
            .BusB(alusrc ? extimm : regoutB),
            .ALUCtrl(aluctrl),
            .Zero(zero)
            );
    
    NextPClogic nextpclogic( // NextPClogic.v
			    .NextPC(nextpc),
			    .CurrentPC(currentpc),
			    .SignExtImm64(extimm),
			    .Branch(branch),
			    .ALUZero(zero),
			    .Uncondbranch(uncond_branch)
			    );

   DataMemory datamemory( // DataMemory.v
			 .ReadData(memoryout),
			 .Address(aluout),
			 .WriteData(regoutB),
			 .MemoryRead(memread),
			 .MemoryWrite(memwrite),
			 .Clock(CLK)
			 );


   SignExtender signext( // SignExtender.v
			.BusImm(extimm),
			.Imm26(instruction[25:0]),
			.Ctrl(signop[2:0])
			);
                


endmodule

SingleCycleProcTest.v
`timescale 1ns / 1ps

`define STRLEN 32
`define HalfClockPeriod 60
`define ClockPeriod `HalfClockPeriod * 2

module SingleCycleProcTest_v;

   initial
     begin
        $dumpfile("singlecycle.vcd");
        $dumpvars;
     end

   // These tasks are used to check if a given test has passed and
   // confirm that all tests passed.
   task passTest;
      input [63:0] actualOut, expectedOut;
      input [`STRLEN*8:0] testType;
      inout [7:0] 	  passed;

      if(actualOut == expectedOut) begin $display ("%s passed", testType); passed = passed + 1; end
      else $display ("%s failed: 0x%x should be 0x%x", testType, actualOut, expectedOut);
   endtask

   task allPassed;
      input [7:0] passed;
      input [7:0] numTests;

      if(passed == numTests) $display ("All tests passed");
      else $display("Some tests failed: %d of %d passed", passed, numTests);
   endtask

   // Inputs
   reg 		  CLK;
   reg 		  Reset_L;
   reg [63:0] 	  startPC;
   reg [7:0] 	  passed;
   reg [15:0] 	  watchdog;

   // Outputs
   wire [63:0] 	  MemtoRegOut;
   wire [63:0] 	  currentPC;

   // Instantiate the Unit Under Test (UUT)
   singlecycle uut (
		    .CLK(CLK),
		    .resetl(Reset_L),
		    .startpc(startPC),
		    .currentpc(currentPC),
		    .MemtoRegOut(MemtoRegOut)
		    );

   initial begin
      // Initialize Inputs
      Reset_L = 1;
      startPC = 0;
      passed = 0;

      // Initialize Watchdog timer
      watchdog = 0;

      // Wait for global reset
      #(1 * `ClockPeriod);

      // Program 1
      #1
        Reset_L = 0; startPC = 0;
      @(posedge CLK);
      @(negedge CLK);
      @(posedge CLK);
      Reset_L = 1;

      // ***********************************************************
      // This while loop will continue cycling the processor until the
      // PC reaches the final instruction in the first test.  If the
      // program forms an infinite loop, never reaching the end, the
      // watchdog timer will kick in and kill simulation after 64K
      // cycles.
      // ***********************************************************

      while (currentPC < 64'h30)
        begin
	   @(posedge CLK);
	   @(negedge CLK);
           $display("CurrentPC:%h",currentPC);
        end
      passTest(MemtoRegOut, 64'hF, "Results of Program 1", passed);

      // ***********************************************************
      // Add your new tests here
      // ***********************************************************

      while (currentPC < 64'h5c)
        begin
	   @(posedge CLK);
	   @(negedge CLK);
           $display("CurrentPC:%h",currentPC);
        end
      passTest(MemtoRegOut, 64'h123456789abcdef0, "Results of Program 2", passed);
      
      // Done
      allPassed(passed, 2);   // Be sure to change the one to match
      // the number of tests you add.
      $finish;
   end

   // Initialize the clock to be 0
   initial begin
      CLK = 0;
   end

   // The following is correct if clock starts at LOW level at StartTime //
   always begin
      #`HalfClockPeriod CLK = ~CLK;
      #`HalfClockPeriod CLK = ~CLK;
      watchdog = watchdog +1;
   end

   // Kill the simulation if the watchdog hits 64K cycles
   always @*
     if (watchdog == 16'hFF)
       begin
          $display("Watchdog Timer Expired.");
          $finish;
       end


endmodule

singlecycle.vcd
$date
	Wed Nov 29 13:50:12 2023
$end
$version
	Icarus Verilog
$end
$timescale
	1ps
$end
$scope module SingleCycleProcTest_v $end
$var wire 64 ! currentPC [63:0] $end
$var wire 64 " MemtoRegOut [63:0] $end
$var reg 1 # CLK $end
$var reg 1 $ Reset_L $end
$var reg 8 % passed [7:0] $end
$var reg 64 & startPC [63:0] $end
$var reg 16 ' watchdog [15:0] $end
$scope module uut $end
$var wire 1 # CLK $end
$var wire 1 $ resetl $end
$var wire 64 ( startpc [63:0] $end
$var wire 1 ) zero $end
$var wire 1 * uncond_branch $end
$var wire 3 + signop [2:0] $end
$var wire 5 , rn [4:0] $end
$var wire 5 - rm [4:0] $end
$var wire 1 . regwrite $end
$var wire 64 / regoutB [63:0] $end
$var wire 64 0 regoutA [63:0] $end
$var wire 1 1 reg2loc $end
$var wire 5 2 rd [4:0] $end
$var wire 11 3 opcode [10:0] $end
$var wire 64 4 nextpc [63:0] $end
$var wire 1 5 memwrite $end
$var wire 1 6 memread $end
$var wire 64 7 memoryout [63:0] $end
$var wire 1 8 mem2reg $end
$var wire 32 9 instruction [31:0] $end
$var wire 64 : extimm [63:0] $end
$var wire 1 ; branch $end
$var wire 1 < alusrc $end
$var wire 64 = aluout [63:0] $end
$var wire 4 > aluctrl [3:0] $end
$var wire 64 ? aluMUXout [63:0] $end
$var wire 64 @ MemtoRegOut [63:0] $end
$var reg 64 A currentpc [63:0] $end
$scope module alu $end
$var wire 64 B BusB [63:0] $end
$var wire 1 ) Zero $end
$var wire 64 C BusA [63:0] $end
$var wire 4 D ALUCtrl [3:0] $end
$var reg 64 E BusW [63:0] $end
$upscope $end
$scope module control $end
$var wire 11 F opcode [10:0] $end
$var reg 4 G aluop [3:0] $end
$var reg 1 < alusrc $end
$var reg 1 ; branch $end
$var reg 1 8 mem2reg $end
$var reg 1 6 memread $end
$var reg 1 5 memwrite $end
$var reg 1 1 reg2loc $end
$var reg 1 . regwrite $end
$var reg 3 H signop [2:0] $end
$var reg 1 * uncond_branch $end
$upscope $end
$scope module datamemory $end
$var wire 64 I Address [63:0] $end
$var wire 1 # Clock $end
$var wire 1 6 MemoryRead $end
$var wire 1 5 MemoryWrite $end
$var wire 64 J WriteData [63:0] $end
$var reg 64 K ReadData [63:0] $end
$scope task initset $end
$var reg 64 L addr [63:0] $end
$var reg 64 M data [63:0] $end
$upscope $end
$upscope $end
$scope module imem $end
$var wire 64 N Address [63:0] $end
$var reg 32 O Data [31:0] $end
$upscope $end
$scope module nextpclogic $end
$var wire 1 ) ALUZero $end
$var wire 1 ; Branch $end
$var wire 64 P CurrentPC [63:0] $end
$var wire 1 * Uncondbranch $end
$var wire 1 Q and1 $end
$var wire 1 R or1 $end
$var wire 64 S SignExtImm64 [63:0] $end
$var reg 64 T NextPC [63:0] $end
$upscope $end
$scope module regfile $end
$var wire 64 U BusA [63:0] $end
$var wire 64 V BusB [63:0] $end
$var wire 64 W BusW [63:0] $end
$var wire 1 # Clk $end
$var wire 5 X RA [4:0] $end
$var wire 5 Y RB [4:0] $end
$var wire 5 Z RW [4:0] $end
$var wire 1 . RegWr $end
$upscope $end
$scope module signext $end
$var wire 3 [ Ctrl [2:0] $end
$var wire 26 \ Imm26 [25:0] $end
$var wire 64 ] BusImm [63:0] $end
$upscope $end
$upscope $end
$scope task allPassed $end
$var reg 8 ^ numTests [7:0] $end
$var reg 8 _ passed [7:0] $end
$upscope $end
$scope task passTest $end
$var reg 64 ` actualOut [63:0] $end
$var reg 64 a expectedOut [63:0] $end
$var reg 8 b passed [7:0] $end
$var reg 257 c testType [256:0] $end
$upscope $end
$upscope $end
$enddefinitions $end
#0
$dumpvars
bx c
bx b
bx a
bx `
bx _
bx ^
bx ]
bx \
bx [
bx Z
bx Y
bx X
bx W
bx V
bx U
bx T
bx S
xR
xQ
bx P
bx O
bx N
b0 M
b100000 L
bx K
bx J
bx I
bx H
bx G
bx F
bx E
bx D
bx C
bx B
bx A
bx @
bx ?
bx >
bx =
x<
x;
bx :
bx 9
x8
bx 7
x6
x5
bx 4
bx 3
bx 2
x1
bx 0
bx /
x.
bx -
bx ,
bx +
x*
x)
b0 (
b0 '
b0 &
b0 %
1$
0#
bx "
bx !
$end
#60000
1#
#120000
b1 '
0#
#121000
0$
#180000
1#
#240000
b10 '
0#
#243000
b0 B
b0 ?
b0 :
b0 S
b0 ]
0R
0Q
b10 +
b10 H
b10 [
b10 >
b10 D
b10 G
1.
1<
05
18
16
0;
0*
b0x00x ,
b0x00x Y
b10000000000001111101001 \
b11111000010 3
b11111000010 F
b11111 -
b11111 X
b1001 2
b1001 Z
b11111000010000000000001111101001 9
b11111000010000000000001111101001 O
b100 4
b100 T
b0 !
b0 A
b0 N
b0 P
#245000
1)
b0 =
b0 E
b0 I
b0 0
b0 C
b0 U
#300000
b1 "
b1 @
b1 W
b1 7
b1 K
1$
1#
#360000
b11 '
0#
#363000
0)
b1000 =
b1000 E
b1000 I
b1000 B
b1000 ?
b1000 :
b1000 S
b1000 ]
b0x0x0 ,
b0x0x0 Y
b10000001000001111101010 \
b1010 2
b1010 Z
b11111000010000001000001111101010 9
b11111000010000001000001111101010 O
b1000 4
b1000 T
b100 !
b100 A
b100 N
b100 P
#420000
b1010 "
b1010 @
b1010 W
b1010 7
b1010 K
1#
#480000
b100 '
0#
#483000
b10000 =
b10000 E
b10000 I
b10000 B
b10000 ?
b10000 :
b10000 S
b10000 ]
b0x0x1 ,
b0x0x1 Y
b10000010000001111101011 \
b1011 2
b1011 Z
b11111000010000010000001111101011 9
b11111000010000010000001111101011 O
b1100 4
b1100 T
b1000 !
b1000 A
b1000 N
b1000 P
#540000
b101 "
b101 @
b101 W
b101 7
b101 K
1#
#600000
b101 '
0#
#603000
b11000 =
b11000 E
b11000 I
b11000 B
b11000 ?
b11000 :
b11000 S
b11000 ]
b0xx0x ,
b0xx0x Y
b10000011000001111101100 \
b1100 2
b1100 Z
b11111000010000011000001111101100 9
b11111000010000011000001111101100 O
b10000 4
b10000 T
b1100 !
b1100 A
b1100 N
b1100 P
#660000
b111111111011111010100111110111101010110110111110111011111111 "
b111111111011111010100111110111101010110110111110111011111111 @
b111111111011111010100111110111101010110110111110111011111111 W
b111111111011111010100111110111101010110110111110111011111111 7
b111111111011111010100111110111101010110110111110111011111111 K
1#
#720000
b110 '
0#
#723000
b100000 =
b100000 E
b100000 I
b100000 B
b100000 ?
b100000 :
b100000 S
b100000 ]
b0xxxx ,
b0xxxx Y
b10000100000001111101101 \
b1101 2
b1101 Z
b11111000010000100000001111101101 9
b11111000010000100000001111101101 O
b10100 4
b10100 T
b10000 !
b10000 A
b10000 N
b10000 P
#780000
b0 "
b0 @
b0 W
b0 7
b0 K
1#
#840000
b111 '
0#
#843000
bx00000x0xx0x0xx0xxxxxxx0x0 :
bx00000x0xx0x0xx0xxxxxxx0x0 S
bx00000x0xx0x0xx0xxxxxxx0x0 ]
x)
bx =
bx E
bx I
bx B
bx ?
bx "
bx @
bx W
bx +
bx H
bx [
b1 >
b1 D
b1 G
0<
08
06
01
b1011 ,
b1011 Y
b10000010110000000101001010 \
b10101010000 3
b10101010000 F
b1010 -
b1010 X
b1010 2
b1010 Z
b10101010000010110000000101001010 9
b10101010000010110000000101001010 O
b11000 4
b11000 T
b10100 !
b10100 A
b10100 N
b10100 P
#845000
b1111 "
b1111 @
b1111 W
b101 B
b101 ?
0)
b1111 =
b1111 E
b1111 I
b101 /
b101 J
b101 V
b1010 0
b1010 C
b1010 U
#900000
1#
#960000
b1000 '
0#
#963000
b0 "
b0 @
b0 W
1)
b0 =
b0 E
b0 I
bx00000xxx00x0x00xxx0x0xx00 :
bx00000xxx00x0x00xxx0x0xx00 S
bx00000xxx00x0x00xxx0x0xx00 ]
b0 >
b0 D
b0 G
b1010 ,
b1010 Y
b10000010100000000110001100 \
b10001010000 3
b10001010000 F
b1100 -
b1100 X
b1100 2
b1100 Z
b10001010000010100000000110001100 9
b10001010000010100000000110001100 O
b11100 4
b11100 T
b11000 !
b11000 A
b11000 N
b11000 P
#965000
b1111 "
b1111 @
b1111 W
b1111 B
b1111 ?
0)
b1111 =
b1111 E
b1111 I
b1111 /
b1111 J
b1111 V
b111111111011111010100111110111101010110110111110111011111111 0
b111111111011111010100111110111101010110110111110111011111111 C
b111111111011111010100111110111101010110110111110111011111111 U
#1020000
1#
#1080000
b1001 '
0#
#1083000
b0xxxx "
b0xxxx @
b0xxxx W
b100 :
b100 S
b100 ]
b1 +
b1 H
b1 [
b111 >
b111 D
b111 G
0.
x8
1;
11
b1100 ,
b1100 Y
b10001100 \
b10110100000 3
b10110100000 F
b100 -
b100 X
b10110100000000000000000010001100 9
b10110100000000000000000010001100 O
b100000 4
b100000 T
b11100 !
b11100 A
b11100 N
b11100 P
#1085000
bx 0
bx C
bx U
#1140000
1#
#1200000
b1010 '
0#
